easymongodb/__init__.py
easymongodb/easymongodb.py
easymongodb-0.1.dist-info/METADATA
easymongodb-0.1.dist-info/WHEEL
easymongodb-0.1.dist-info/top_level.txt
easymongodb-0.1.dist-info/RECORD
